{
  "notes": [
    {
      "dateOfInterview": "2020-10-23",
      "timestamp": 1603385521409,
      "author": "Marques Balistreri",
      "suspect": "Jozie",
      "note": "She seems innocent, but things are not always what they seem.",
      "id": 1
    },
    {
      "dateOfInterview": "2020-10-22",
      "timestamp": 1603393348900,
      "author": "Marques Balistreri",
      "suspect": "Nathanial Dach",
      "note": "Nathaniel is seems like he is hiding a lot more than he is admitting to.",
      "id": 2
    },
    {
      "dateOfInterview": "2020-10-08",
      "timestamp": 1603393420826,
      "author": "Alessia Bailey",
      "suspect": "Ubaldo Dayle",
      "note": "Ubaldo has dead eyes, When I look into those eyes I feel like my soul is being sucked out of me.",
      "id": 3
    },
    {
      "dateOfInterview": "2020-10-27",
      "timestamp": 1603815716935,
      "author": "Marques Balistreri",
      "suspect": "Madelyn Lesback",
      "note": "I cant believe she stole a car and got 16 years!",
      "id": 4
    },
    {
      "dateOfInterview": "2020-11-02",
      "timestamp": 1604794753107,
      "author": "billy",
      "suspect": "bobby",
      "note": "billybobby",
      "id": 5
    }
  ]
}